{"updated_at": "2026-03-28T05:46:56.058373+00:00", "value": {"connections": {"Australia": {"energy": ["refined_petroleum", "crude_petroleum", "petroleum_gas"], "food": ["milk", "wheat", "frozen_bovine_meat"]}, "Brazil": {"energy": [], "food": ["poultry_meat", "frozen_bovine_meat"]}, "India": {"energy": [], "food": ["rice", "milk", "frozen_bovine_meat"]}, "Malaysia": {"energy": ["refined_petroleum", "petroleum_gas", "crude_petroleum", "coal_tar_oil"], "food": ["poultry_meat", "milk", "wheat", "palm_oil", "frozen_bovine_meat"]}, "Saudi Arabia": {"energy": ["refined_petroleum", "crude_petroleum", "petroleum_gas"], "food": []}, "Thailand": {"energy": [], "food": ["rice", "poultry_meat", "milk"]}, "United Arab Emirates": {"energy": ["refined_petroleum", "crude_petroleum", "petroleum_gas"], "food": []}, "United States": {"energy": ["refined_petroleum", "crude_petroleum", "petroleum_gas"], "food": []}}, "source": "live"}}